{
  "_meta": {
    "sources": [
      "loopback/common/models",
      "loopback/server/models",
      "../common/models",
      "./models"
    ],
    "mixins": [
      "loopback/common/mixins",
      "loopback/server/mixins",
      "../node_modules/loopback-ds-timestamp-mixin",
      "../common/mixins",
      "./mixins"
    ]
  },
  "User": {
    "dataSource": "db"
  },
  "AccessToken": {
    "dataSource": "db",
    "public": false
  },
  "ACL": {
    "dataSource": "db",
    "public": false
  },
  "RoleMapping": {
    "dataSource": "db",
    "public": false,
    "options": {
      "strictObjectIDCoercion": true
    }
  },
  "Role": {
    "dataSource": "db",
    "public": false
  },
  "product": {
    "dataSource": "mongo_local",
    "public": true
  },
  "impost": {
    "dataSource": "mongo_local",
    "public": true
  },
  "category": {
    "dataSource": "mongo_local",
    "public": true
  },
  "unity": {
    "dataSource": "mongo_local",
    "public": true
  },
  "type": {
    "dataSource": "mongo_local",
    "public": true
  },
  "packaging": {
    "dataSource": "mongo_local",
    "public": true
  },
  "categoryremote": {
    "dataSource": "mongo_cloud",
    "public": true
  },
  "impostremote": {
    "dataSource": "mongo_cloud",
    "public": true
  },
  "packagingremote": {
    "dataSource": "mongo_cloud",
    "public": true
  },
  "productremote": {
    "dataSource": "mongo_cloud",
    "public": true
  },
  "typeremote": {
    "dataSource": "mongo_cloud",
    "public": true
  },
  "unityremote": {
    "dataSource": "mongo_cloud",
    "public": true
  }
}
